[{"line":2,"elements":[{"line":3,"name":"User open staging-Cicle app on Mobile","description":"","type":"background","keyword":"Background","steps":[]},{"start_timestamp":"2023-01-04T01:23:55.654Z","line":6,"name":"User search jump to Search team (web team)","description":"","id":"feature-to-test-search-functionality;user-search-jump-to-search-team-(web-team)","type":"scenario","keyword":"Scenario","steps":[{"result":{"duration":7288000000,"status":"passed"},"line":7,"name":"User open staging-cicle on mobile","match":{"location":"MyStepdefs.BaseTest.userOpenStagingCicleOnMobile()"},"keyword":"Given "},{"result":{"duration":7779000000,"status":"passed"},"line":8,"name":"User click search menu","match":{"location":"MyStepdefs.SearchTest.userClickSearchMenu()"},"keyword":"When "},{"result":{"duration":6003000000,"status":"passed"},"line":9,"name":"User type search","match":{"location":"MyStepdefs.SearchTest.userTypeSearch()"},"keyword":"And "},{"result":{"duration":2110000000,"status":"passed"},"line":10,"name":"User choose team","match":{"location":"MyStepdefs.SearchTest.userChooseTeam()"},"keyword":"And "},{"result":{"duration":5233000000,"status":"passed"},"line":11,"name":"User successfully jump to search team","match":{"location":"MyStepdefs.SearchTest.userSuccessfullyJumpToSearchTeam()"},"keyword":"Then "}],"tags":[{"name":"@SearchPositive"},{"name":"@Positive01"}]},{"line":3,"name":"User open staging-Cicle app on Mobile","description":"","type":"background","keyword":"Background","steps":[]},{"start_timestamp":"2023-01-04T01:24:24.194Z","line":14,"name":"User search jump to Search kanban (web team)","description":"","id":"feature-to-test-search-functionality;user-search-jump-to-search-kanban-(web-team)","type":"scenario","keyword":"Scenario","steps":[{"result":{"duration":8200000000,"status":"passed"},"line":15,"name":"User open staging-cicle on mobile","match":{"location":"MyStepdefs.BaseTest.userOpenStagingCicleOnMobile()"},"keyword":"Given "},{"result":{"duration":7761000000,"status":"passed"},"line":16,"name":"User click search menu","match":{"location":"MyStepdefs.SearchTest.userClickSearchMenu()"},"keyword":"When "},{"result":{"duration":6103000000,"status":"passed"},"line":17,"name":"User type search","match":{"location":"MyStepdefs.SearchTest.userTypeSearch()"},"keyword":"And "},{"result":{"duration":2149000000,"status":"passed"},"line":18,"name":"User choose kanban","match":{"location":"MyStepdefs.SearchTest.userChooseKanban()"},"keyword":"And "},{"result":{"duration":5277000000,"status":"passed"},"line":19,"name":"User successfully jump to search kanban","match":{"location":"MyStepdefs.SearchTest.userSuccessfullyJumpToSearchKanban()"},"keyword":"Then "}],"tags":[{"name":"@SearchPositive"},{"name":"@Positive02"}]},{"line":3,"name":"User open staging-Cicle app on Mobile","description":"","type":"background","keyword":"Background","steps":[]},{"start_timestamp":"2023-01-04T01:24:53.701Z","line":22,"name":"User search jump to Search blast (web team)","description":"","id":"feature-to-test-search-functionality;user-search-jump-to-search-blast-(web-team)","type":"scenario","keyword":"Scenario","steps":[{"result":{"duration":8218000000,"status":"passed"},"line":23,"name":"User open staging-cicle on mobile","match":{"location":"MyStepdefs.BaseTest.userOpenStagingCicleOnMobile()"},"keyword":"Given "},{"result":{"duration":7688000000,"status":"passed"},"line":24,"name":"User click search menu","match":{"location":"MyStepdefs.SearchTest.userClickSearchMenu()"},"keyword":"When "},{"result":{"duration":65250000000,"status":"passed"},"line":25,"name":"User type search","match":{"location":"MyStepdefs.SearchTest.userTypeSearch()"},"keyword":"And "},{"result":{"duration":2085000000,"status":"passed"},"line":26,"name":"User choose blast","match":{"location":"MyStepdefs.SearchTest.userChooseBlast()"},"keyword":"And "},{"result":{"duration":35040000000,"status":"passed"},"line":27,"name":"User successfully jump to search blast","match":{"location":"MyStepdefs.SearchTest.userSuccessfullyJumpToSearchBlast()"},"keyword":"Then "}],"tags":[{"name":"@SearchPositive"},{"name":"@Positive03"}]},{"line":3,"name":"User open staging-Cicle app on Mobile","description":"","type":"background","keyword":"Background","steps":[]},{"start_timestamp":"2023-01-04T01:26:51.998Z","line":30,"name":"User search jump to Search schedules (web team)","description":"","id":"feature-to-test-search-functionality;user-search-jump-to-search-schedules-(web-team)","type":"scenario","keyword":"Scenario","steps":[{"result":{"duration":8166000000,"status":"passed"},"line":31,"name":"User open staging-cicle on mobile","match":{"location":"MyStepdefs.BaseTest.userOpenStagingCicleOnMobile()"},"keyword":"Given "},{"result":{"duration":7757000000,"status":"passed"},"line":32,"name":"User click search menu","match":{"location":"MyStepdefs.SearchTest.userClickSearchMenu()"},"keyword":"When "},{"result":{"duration":7043000000,"status":"passed"},"line":33,"name":"User type search","match":{"location":"MyStepdefs.SearchTest.userTypeSearch()"},"keyword":"And "},{"result":{"duration":2109000000,"status":"passed"},"line":34,"name":"User choose schedules","match":{"location":"MyStepdefs.SearchTest.userChooseSchedules()"},"keyword":"And "},{"result":{"duration":5154000000,"status":"passed"},"line":35,"name":"User successfully jump to search schedules","match":{"location":"MyStepdefs.SearchTest.userSuccessfullyJumpToSearchSchedules()"},"keyword":"Then "}],"tags":[{"name":"@SearchPositive"},{"name":"@Positive04"}]},{"line":3,"name":"User open staging-Cicle app on Mobile","description":"","type":"background","keyword":"Background","steps":[]},{"start_timestamp":"2023-01-04T01:27:22.243Z","line":38,"name":"User search jump to Search checkin (web team)","description":"","id":"feature-to-test-search-functionality;user-search-jump-to-search-checkin-(web-team)","type":"scenario","keyword":"Scenario","steps":[{"result":{"duration":8082000000,"status":"passed"},"line":39,"name":"User open staging-cicle on mobile","match":{"location":"MyStepdefs.BaseTest.userOpenStagingCicleOnMobile()"},"keyword":"Given "},{"result":{"duration":7750000000,"status":"passed"},"line":40,"name":"User click search menu","match":{"location":"MyStepdefs.SearchTest.userClickSearchMenu()"},"keyword":"When "},{"result":{"duration":5943000000,"status":"passed"},"line":41,"name":"User type search","match":{"location":"MyStepdefs.SearchTest.userTypeSearch()"},"keyword":"And "},{"result":{"duration":2191000000,"status":"passed"},"line":42,"name":"User choose checkin","match":{"location":"MyStepdefs.SearchTest.userChooseCheckin()"},"keyword":"And "},{"result":{"duration":5247000000,"status":"passed"},"line":43,"name":"User successfully jump to search checkin","match":{"location":"MyStepdefs.SearchTest.userSuccessfullyJumpToSearchCheckin()"},"keyword":"Then "}],"tags":[{"name":"@SearchPositive"},{"name":"@Positive05"}]},{"line":3,"name":"User open staging-Cicle app on Mobile","description":"","type":"background","keyword":"Background","steps":[]},{"start_timestamp":"2023-01-04T01:27:51.463Z","line":46,"name":"User search jump to Search groupchat web team)","description":"","id":"feature-to-test-search-functionality;user-search-jump-to-search-groupchat-web-team)","type":"scenario","keyword":"Scenario","steps":[{"result":{"duration":8172000000,"status":"passed"},"line":47,"name":"User open staging-cicle on mobile","match":{"location":"MyStepdefs.BaseTest.userOpenStagingCicleOnMobile()"},"keyword":"Given "},{"result":{"duration":7843000000,"status":"passed"},"line":48,"name":"User click search menu","match":{"location":"MyStepdefs.SearchTest.userClickSearchMenu()"},"keyword":"When "},{"result":{"duration":5513000000,"status":"passed"},"line":49,"name":"User type search","match":{"location":"MyStepdefs.SearchTest.userTypeSearch()"},"keyword":"And "},{"result":{"duration":2250000000,"status":"passed"},"line":50,"name":"User choose groupchat","match":{"location":"MyStepdefs.SearchTest.userChooseGroupchat()"},"keyword":"And "},{"result":{"duration":5432000000,"status":"passed"},"line":51,"name":"User successfully jump to search groupchat","match":{"location":"MyStepdefs.SearchTest.userSuccessfullyJumpToSearchGroupchat()"},"keyword":"Then "}],"tags":[{"name":"@SearchPositive"},{"name":"@Positive06"}]},{"line":3,"name":"User open staging-Cicle app on Mobile","description":"","type":"background","keyword":"Background","steps":[]},{"start_timestamp":"2023-01-04T01:28:20.681Z","line":54,"name":"User search jump to Search doc and file","description":"","id":"feature-to-test-search-functionality;user-search-jump-to-search-doc-and-file","type":"scenario","keyword":"Scenario","steps":[{"result":{"duration":8039000000,"status":"passed"},"line":55,"name":"User open staging-cicle on mobile","match":{"location":"MyStepdefs.BaseTest.userOpenStagingCicleOnMobile()"},"keyword":"Given "},{"result":{"duration":7736000000,"status":"passed"},"line":56,"name":"User click search menu","match":{"location":"MyStepdefs.SearchTest.userClickSearchMenu()"},"keyword":"When "},{"result":{"duration":5944000000,"status":"passed"},"line":57,"name":"User type search","match":{"location":"MyStepdefs.SearchTest.userTypeSearch()"},"keyword":"And "},{"result":{"duration":2138000000,"status":"passed"},"line":58,"name":"User choose doc and file","match":{"location":"MyStepdefs.SearchTest.userChooseDocAndFile()"},"keyword":"And "},{"result":{"duration":29115000000,"status":"passed"},"line":59,"name":"User successfully jump to search doc and file","match":{"location":"MyStepdefs.SearchTest.userSuccessfullyJumpToSearchDocAndFile()"},"keyword":"Then "}],"tags":[{"name":"@SearchPositive"},{"name":"@Positive07"}]}],"name":"feature to test search functionality","description":"","id":"feature-to-test-search-functionality","keyword":"Feature","uri":"file:src/test/resources/Features/SearchPositive.feature","tags":[{"name":"@SearchPositive","type":"Tag","location":{"line":1,"column":1}}]}]